careful/__init__.py
careful/httpx/__init__.py
careful/httpx/_types.py
careful/httpx/dev_cache.py
careful/httpx/py.typed
careful/httpx/retries.py
careful/httpx/throttle.py
careful-0.2.1.dist-info/METADATA
careful-0.2.1.dist-info/WHEEL
careful-0.2.1.dist-info/licenses/LICENSE
careful-0.2.1.dist-info/RECORD
