Metadata-Version: 2.4
Name: careful
Version: 0.2.1
Summary: careful extensions to httpx: throttle, retry, cache
Project-URL: Repository, https://codeberg.org/jpt/careful
Author-email: jpt <dev@jpt.sh>
License: BSD-2-Clause
License-File: LICENSE
Classifier: Development Status :: 6 - Mature
Classifier: Intended Audience :: Developers
Classifier: License :: OSI Approved :: BSD License
Classifier: Natural Language :: English
Classifier: Operating System :: OS Independent
Classifier: Programming Language :: Python :: 3.10
Classifier: Programming Language :: Python :: 3.11
Classifier: Programming Language :: Python :: 3.12
Classifier: Programming Language :: Python :: 3.13
Classifier: Topic :: Software Development :: Libraries :: Python Modules
Requires-Python: >=3.10
Requires-Dist: httpx>=0.28.1
